strands_telegram_listener/__init__.py
strands_telegram_listener/telegram_listener.py
strands_telegram_listener-1.0.1.dist-info/licenses/LICENSE
strands_telegram_listener-1.0.1.dist-info/METADATA
strands_telegram_listener-1.0.1.dist-info/WHEEL
strands_telegram_listener-1.0.1.dist-info/top_level.txt
strands_telegram_listener-1.0.1.dist-info/RECORD
