Metadata-Version: 2.4
Name: strands-telegram-listener
Version: 1.0.1
Summary: Real-time Telegram message processing with AI-powered responses for Strands Agents
Author-email: Strands Community <community@strandsagents.com>
License: MIT
Project-URL: Homepage, https://github.com/eraykeskinmac/strands-telegram-listener
Project-URL: Documentation, https://github.com/eraykeskinmac/strands-telegram-listener#readme
Project-URL: Repository, https://github.com/eraykeskinmac/strands-telegram-listener.git
Project-URL: Bug Tracker, https://github.com/eraykeskinmac/strands-telegram-listener/issues
Project-URL: Changelog, https://github.com/eraykeskinmac/strands-telegram-listener/blob/main/CHANGELOG.md
Keywords: strands,agents,telegram,bot,listener,ai,realtime,messaging,automation,background,polling,events
Classifier: Development Status :: 5 - Production/Stable
Classifier: Intended Audience :: Developers
Classifier: License :: OSI Approved :: MIT License
Classifier: Operating System :: OS Independent
Classifier: Programming Language :: Python :: 3
Classifier: Programming Language :: Python :: 3.8
Classifier: Programming Language :: Python :: 3.9
Classifier: Programming Language :: Python :: 3.10
Classifier: Programming Language :: Python :: 3.11
Classifier: Programming Language :: Python :: 3.12
Classifier: Topic :: Communications :: Chat
Classifier: Topic :: Internet :: WWW/HTTP :: Dynamic Content
Classifier: Topic :: Software Development :: Libraries :: Python Modules
Classifier: Topic :: Scientific/Engineering :: Artificial Intelligence
Classifier: Topic :: System :: Monitoring
Requires-Python: >=3.8
License-File: LICENSE
Requires-Dist: strands-agents
Requires-Dist: requests>=2.25.0
Provides-Extra: dev
Requires-Dist: pytest>=7.0.0; extra == "dev"
Requires-Dist: pytest-cov>=4.0.0; extra == "dev"
Requires-Dist: pytest-asyncio>=0.20.0; extra == "dev"
Requires-Dist: black>=22.0.0; extra == "dev"
Requires-Dist: isort>=5.10.0; extra == "dev"
Requires-Dist: flake8>=5.0.0; extra == "dev"
Requires-Dist: mypy>=1.0.0; extra == "dev"
Requires-Dist: pre-commit>=2.17.0; extra == "dev"
Provides-Extra: test
Requires-Dist: pytest>=7.0.0; extra == "test"
Requires-Dist: pytest-cov>=4.0.0; extra == "test"
Requires-Dist: pytest-asyncio>=0.20.0; extra == "test"
Requires-Dist: responses>=0.23.0; extra == "test"
Requires-Dist: pytest-mock>=3.10.0; extra == "test"
Requires-Dist: pytest-threading>=0.1.0; extra == "test"
Provides-Extra: telegram
Requires-Dist: strands-telegram>=1.0.0; extra == "telegram"
Dynamic: license-file
